blackfish-0.3.12.dist-info/METADATA
blackfish-0.3.12.dist-info/WHEEL
blackfish-0.3.12.dist-info/licenses/LICENSE
blackfish/__init__.py
blackfish/orca_parser.py
blackfish/parsing/soc_states.py
blackfish/parsing/tddft_absorption_spectrum.py
blackfish/parsing/energies.py
blackfish/parsing/__init__.py
blackfish/parsing/ir_spectrum.py
blackfish/parsing/nacme.py
blackfish/parsing/socme.py
blackfish/parsing/casscf.py
blackfish/parsing/utilities.py
blackfish/parsing/soc_absorption_spectrum.py
blackfish/parsing/roots.py
blackfish/apps/ailft.py
blackfish/apps/frequency_analysis.py
blackfish/apps/__init__.py
blackfish/apps/ir.py
blackfish/apps/gaussian_broadening.py
blackfish/apps/soc_absorption_spectrum.py
blackfish/apps/rust.py
blackfish/blackfish.cpython-312-darwin.so
blackfish-0.3.12.dist-info/RECORD
