Metadata-Version: 2.4
Name: blackfish
Version: 0.3.12
Requires-Dist: altair>=5.5.0
Requires-Dist: marimo>=0.10.9
Requires-Dist: maturin>=1.0,<2.0
Requires-Dist: numpy>=2.2.1
Requires-Dist: polars>=1.18.0
Requires-Dist: pytest>=8.3.4
Requires-Dist: scipy>=1.14.1
License-File: LICENSE
Summary: ORCA quantum chemistry data parser
Author-email: Frederik Scherz <frederik.scherz@gmail.de>
License: Apache-2.0
Requires-Python: >=3.12
Project-URL: repository, https://codeberg.org/crabby/blackfish
